hearbaseline/__init__.py
hearbaseline/naive.py
hearbaseline/torchcrepe.py
hearbaseline/torchopenl3.py
hearbaseline/util.py
hearbaseline/vggish.py
hearbaseline/vqt.py
hearbaseline/wav2vec2.py
hearbaseline/keras/__init__.py
hearbaseline/keras/naive.py
hearbaseline/tf/__init__.py
hearbaseline/tf/naive.py
hearbaseline/tf/util.py
hearbaseline-2021.1.1.dist-info/LICENSE
hearbaseline-2021.1.1.dist-info/METADATA
hearbaseline-2021.1.1.dist-info/WHEEL
hearbaseline-2021.1.1.dist-info/top_level.txt
hearbaseline-2021.1.1.dist-info/RECORD
