Metadata-Version: 2.1
Name: hearbaseline
Version: 2021.1.1
Summary: Holistic Evaluation of Audio Representations (HEAR) 2021 -- Baseline Model
Home-page: https://github.com/hearbenchmark/hear-baseline
Author: HEAR 2021 NeurIPS Competition Committee
Author-email: deep@neuralaudio.ai
License: Apache-2.0
Project-URL: Bug Tracker, https://github.com/hearbenchmark/hear-baseline/issues
Project-URL: Source Code, https://github.com/hearbenchmark/hear-baseline
Requires-Python: >=3.7
License-File: LICENSE
Requires-Dist: librosa
Requires-Dist: numba (==0.48)
Requires-Dist: numpy (==1.19.2)
Requires-Dist: tensorflow (>=2.0)
Requires-Dist: torch
Requires-Dist: speechbrain
Requires-Dist: transformers
Requires-Dist: torchcrepe
Requires-Dist: torchopenl3
Requires-Dist: scikit-learn (>=0.24.2)
Provides-Extra: dev
Requires-Dist: pre-commit ; extra == 'dev'
Requires-Dist: black ; extra == 'dev'
Requires-Dist: pytest ; extra == 'dev'
Requires-Dist: pytest-cov ; extra == 'dev'
Requires-Dist: pytest-env ; extra == 'dev'
Provides-Extra: test
Requires-Dist: pytest ; extra == 'test'
Requires-Dist: pytest-cov ; extra == 'test'
Requires-Dist: pytest-env ; extra == 'test'
